lzdata/__init__.py
lzdata/cli.py
lzdata-0.0.1.dist-info/LICENSE
lzdata-0.0.1.dist-info/METADATA
lzdata-0.0.1.dist-info/WHEEL
lzdata-0.0.1.dist-info/entry_points.txt
lzdata-0.0.1.dist-info/top_level.txt
lzdata-0.0.1.dist-info/RECORD
