Metadata-Version: 2.2
Name: lzdata
Version: 0.0.1
Summary: Lazy data validation and transformation.
Author-email: Ian Maurer <imaurer@gmail.com>
Project-URL: Homepage, https://lzkit.com/lzdata/
Project-URL: Repository, https://github.com/lzkit/lzdata
Project-URL: Documentation, https://lzkit.com/lzdata/
Keywords: python
Classifier: Intended Audience :: Developers
Classifier: Programming Language :: Python
Classifier: Programming Language :: Python :: 3
Classifier: Programming Language :: Python :: 3.10
Classifier: Programming Language :: Python :: 3.11
Classifier: Programming Language :: Python :: 3.12
Classifier: Programming Language :: Python :: 3.13
Classifier: Topic :: Software Development :: Libraries :: Python Modules
Requires-Python: <4.0,>=3.10
License-File: LICENSE
Requires-Dist: click>=8.1.8
Provides-Extra: api
